pdSharepoint/__init__.py
pdSharepoint-1.0.0.dist-info/LICENSE
pdSharepoint-1.0.0.dist-info/METADATA
pdSharepoint-1.0.0.dist-info/WHEEL
pdSharepoint-1.0.0.dist-info/top_level.txt
pdSharepoint-1.0.0.dist-info/RECORD
