Metadata-Version: 2.1
Name: pdSharepoint
Version: 1.0.0
Summary: Pacote para obter arquivos excel ou listas do Sharepoint em um DataFrame pandas
Home-page: https://github.com/danielsioli/pdSharepoint
Author: Daniel Oliveira
Author-email: danielsioli@gmail.com
License: Creative Commons Attribution-Noncommercial-Share Alike license
Keywords: Sharepoint,pandas
Platform: UNKNOWN
Classifier: Development Status :: 4 - Beta
Classifier: Intended Audience :: Developers
Classifier: Topic :: Internet :: WWW/HTTP
Classifier: Programming Language :: Python :: 3
Classifier: Programming Language :: Python :: 3.3
Classifier: Programming Language :: Python :: 3.4
Classifier: Programming Language :: Python :: 3.5
Requires-Python: >=3.6
Requires-Dist: O365
Requires-Dist: pandas
Requires-Dist: openpyxl
Requires-Dist: xlrd
